modbus_connect/__init__.py
modbus_connect/core.py
modbus_connect/importer.py
modbus_connect/processors.py
modbus_connect/utils.py
modbus_connect-0.1.2.dist-info/METADATA
modbus_connect-0.1.2.dist-info/LICENSE
modbus_connect-0.1.2.dist-info/WHEEL
modbus_connect-0.1.2.dist-info/RECORD
