Metadata-Version: 2.1
Name: modbus-connect
Version: 0.1.2
Summary: Modbus TCP data acquisition library
Author: Ángel Fernández Sobrino
Author-email: fernandezsobrinoangel@gmail.com
Requires-Python: >=3.11,<4.0
Classifier: License :: OSI Approved :: MIT License
Classifier: Operating System :: OS Independent
Classifier: Programming Language :: Python :: 3
Classifier: Programming Language :: Python :: 3.11
Classifier: Programming Language :: Python :: 3
Requires-Dist: pymodbus (>=3.0.2,<4.0.0)
